session_guard/__init__.py
SessionGuard-0.1.0.dist-info/LICENSE
SessionGuard-0.1.0.dist-info/METADATA
SessionGuard-0.1.0.dist-info/WHEEL
SessionGuard-0.1.0.dist-info/top_level.txt
SessionGuard-0.1.0.dist-info/RECORD
