Metadata-Version: 2.1
Name: SessionGuard
Version: 0.1.0
Summary: SessionGuard is a Python library for secure and efficient session management using Redis.
Author-email: Pedro Cantidio <ppcantidio@gmail.com>
Project-URL: homepage, https://github.com/ppcantidio/SessionGuard.py
Classifier: Development Status :: 3 - Alpha
Classifier: Intended Audience :: Developers
Classifier: License :: OSI Approved :: MIT License
Classifier: Programming Language :: Python :: 3
Classifier: Programming Language :: Python :: 3.6
Classifier: Programming Language :: Python :: 3.7
Classifier: Programming Language :: Python :: 3.8
Classifier: Programming Language :: Python :: 3.9
Classifier: Programming Language :: Python :: 3.10
Classifier: Programming Language :: Python :: 3.11
License-File: LICENSE
